{
  "products": [
    {
      "id": 1,
      "name": "Caneta Bic",
      "price": "2.37"
    },
    {
      "id": 2,
      "name": "Caderno de 10 materia",
      "price": 22.73
    },
    {
      "id": 3,
      "name": "Borracha",
      "price": 1.99
    },
    {
      "name": "Web Front-end",
      "price": "1246.45",
      "id": 4
    },
    {
      "name": "Rinoceronte",
      "price": "345.56416",
      "id": 5
    },
    {
      "name": "Notebook",
      "price": "7548.23",
      "id": 6
    },
    {
      "name": "Ipad",
      "price": "1246.45",
      "id": 7
    }
  ]
}